<?xml version="1.0" encoding="UTF-8" standalone="no" ?>
<!DOCTYPE register-details-file>
<register-details-file xmlns="http://www.freescale.com/schema/ddd/1.0/detail" xmlns:xsi="http://www.w3.org/2001/XMLSchema-instance" xsi:schemaLocation="http://www.freescale.com/schema/ddd/1.0/detail RegisterDetails.xsd">

<register-details>
  <name>SIM_SCGC7</name>
  <bitrange>31:0</bitrange>
  <reset-value>0x3</reset-value>
  <description>System Clock Gating Control Register 7</description>
  <bitfields>
    <bitfield>
      <name>MPU</name>
      <bitrange>0</bitrange>
      <format>binary</format>
      <access>readwrite</access>
      <description>MPU Clock Gate control.</description>
      <values>
        <value>
          <value>0b0</value>
          <description>Clock disabled</description>
        </value>
        <value>
          <value>0b1</value>
          <description>Clock enabled</description>
        </value>
      </values>
    </bitfield>
    <bitfield>
      <name>DMA</name>
      <bitrange>1</bitrange>
      <format>binary</format>
      <access>readwrite</access>
      <description>DMA Clock Gate control.</description>
      <values>
        <value>
          <value>0b0</value>
          <description>Clock disabled</description>
        </value>
        <value>
          <value>0b1</value>
          <description>Clock enabled</description>
        </value>
      </values>
    </bitfield>
    <bitfield>
      <name/>
      <bitrange>31:2</bitrange>
      <format>binary</format>
      <access>read</access>
    </bitfield>
  </bitfields>
</register-details>

</register-details-file>
