<?xml version="1.0" encoding="UTF-8" standalone="no" ?>
<!DOCTYPE register-details-file>
<register-details-file xmlns="http://www.freescale.com/schema/ddd/1.0/detail" xmlns:xsi="http://www.w3.org/2001/XMLSchema-instance" xsi:schemaLocation="http://www.freescale.com/schema/ddd/1.0/detail RegisterDetails.xsd">

<register-details>
  <name>BP_CID1</name>
  <bitrange>31:0</bitrange>
  <reset-value>0xE0</reset-value>
  <description>Component Identification Register 1.</description>
  <bitfields>
    <bitfield>
      <name>Preamble</name>
      <bitrange>3:0</bitrange>
      <format>binary</format>
      <access>read</access>
      <description>Preamble</description>
    </bitfield>
    <bitfield>
      <name>ComponentClass</name>
      <bitrange>7:4</bitrange>
      <format>binary</format>
      <access>read</access>
      <description>Component class</description>
      <values>
        <value>
          <value>0b0001</value>
          <description>ROM table.</description>
        </value>
        <value>
          <value>0b1001</value>
          <description>CoreSight component.</description>
        </value>
        <value>
          <value>0b1111</value>
          <description>PrimeCell of system component with no standardized register layout, for backward compatibility.</description>
        </value>
      </values>
    </bitfield>
    <bitfield>
      <name/>
      <bitrange>8</bitrange>
      <format>binary</format>
      <access>read</access>
      <description>Reserved</description>
    </bitfield>
    <bitfield>
      <name/>
      <bitrange>9</bitrange>
      <format>binary</format>
      <access>read</access>
      <description>Reserved</description>
    </bitfield>
    <bitfield>
      <name/>
      <bitrange>10</bitrange>
      <format>binary</format>
      <access>read</access>
      <description>Reserved</description>
    </bitfield>
    <bitfield>
      <name/>
      <bitrange>11</bitrange>
      <format>binary</format>
      <access>read</access>
      <description>Reserved</description>
    </bitfield>
    <bitfield>
      <name/>
      <bitrange>12</bitrange>
      <format>binary</format>
      <access>read</access>
      <description>Reserved</description>
    </bitfield>
    <bitfield>
      <name/>
      <bitrange>13</bitrange>
      <format>binary</format>
      <access>read</access>
      <description>Reserved</description>
    </bitfield>
    <bitfield>
      <name/>
      <bitrange>14</bitrange>
      <format>binary</format>
      <access>read</access>
      <description>Reserved</description>
    </bitfield>
    <bitfield>
      <name/>
      <bitrange>15</bitrange>
      <format>binary</format>
      <access>read</access>
      <description>Reserved</description>
    </bitfield>
    <bitfield>
      <name/>
      <bitrange>16</bitrange>
      <format>binary</format>
      <access>read</access>
      <description>Reserved</description>
    </bitfield>
    <bitfield>
      <name/>
      <bitrange>17</bitrange>
      <format>binary</format>
      <access>read</access>
      <description>Reserved</description>
    </bitfield>
    <bitfield>
      <name/>
      <bitrange>18</bitrange>
      <format>binary</format>
      <access>read</access>
      <description>Reserved</description>
    </bitfield>
    <bitfield>
      <name/>
      <bitrange>19</bitrange>
      <format>binary</format>
      <access>read</access>
      <description>Reserved</description>
    </bitfield>
    <bitfield>
      <name/>
      <bitrange>20</bitrange>
      <format>binary</format>
      <access>read</access>
      <description>Reserved</description>
    </bitfield>
    <bitfield>
      <name/>
      <bitrange>21</bitrange>
      <format>binary</format>
      <access>read</access>
      <description>Reserved</description>
    </bitfield>
    <bitfield>
      <name/>
      <bitrange>22</bitrange>
      <format>binary</format>
      <access>read</access>
      <description>Reserved</description>
    </bitfield>
    <bitfield>
      <name/>
      <bitrange>23</bitrange>
      <format>binary</format>
      <access>read</access>
      <description>Reserved</description>
    </bitfield>
    <bitfield>
      <name/>
      <bitrange>24</bitrange>
      <format>binary</format>
      <access>read</access>
      <description>Reserved</description>
    </bitfield>
    <bitfield>
      <name/>
      <bitrange>25</bitrange>
      <format>binary</format>
      <access>read</access>
      <description>Reserved</description>
    </bitfield>
    <bitfield>
      <name/>
      <bitrange>26</bitrange>
      <format>binary</format>
      <access>read</access>
      <description>Reserved</description>
    </bitfield>
    <bitfield>
      <name/>
      <bitrange>27</bitrange>
      <format>binary</format>
      <access>read</access>
      <description>Reserved</description>
    </bitfield>
    <bitfield>
      <name/>
      <bitrange>28</bitrange>
      <format>binary</format>
      <access>read</access>
      <description>Reserved</description>
    </bitfield>
    <bitfield>
      <name/>
      <bitrange>29</bitrange>
      <format>binary</format>
      <access>read</access>
      <description>Reserved</description>
    </bitfield>
    <bitfield>
      <name/>
      <bitrange>30</bitrange>
      <format>binary</format>
      <access>read</access>
      <description>Reserved</description>
    </bitfield>
    <bitfield>
      <name/>
      <bitrange>31</bitrange>
      <format>binary</format>
      <access>read</access>
      <description>Reserved</description>
    </bitfield>
  </bitfields>
</register-details>

</register-details-file>
